kitsupublisher/__init__.py
kitsupublisher/__main__.py
kitsupublisher/__version__.py
kitsupublisher/exceptions.py
kitsupublisher/working_context.py
kitsupublisher/resources/__init__.py
kitsupublisher/resources/fonts/Lato-Regular.ttf
kitsupublisher/resources/fonts/Roboto-Regular.ttf
kitsupublisher/resources/images/logo_cgwire.png
kitsupublisher/resources/images/logo_kitsu.png
kitsupublisher/resources/images/icons/no_avatar.png
kitsupublisher/resources/images/icons/open-in-browser.png
kitsupublisher/resources/images/icons/refresh.png
kitsupublisher/resources/translations/README.rst
kitsupublisher/resources/translations/en_US.qm
kitsupublisher/resources/translations/en_US.ts
kitsupublisher/resources/translations/fr_FR.qm
kitsupublisher/resources/translations/fr_FR.ts
kitsupublisher/resources/views/CommentWidget.ui
kitsupublisher/resources/views/Logo.ui
kitsupublisher/resources/views/MainWindow.ui
kitsupublisher/resources/views/PreviewWidget.ui
kitsupublisher/resources/views/TakePreviewWidget.ui
kitsupublisher/resources/views/TaskPanel.ui
kitsupublisher/resources/views/ToolBarWidget.ui
kitsupublisher/software_link/__init__.py
kitsupublisher/software_link/blender/__init__.py
kitsupublisher/software_link/blender/launch_kitsu.py
kitsupublisher/software_link/houdini/123.py
kitsupublisher/software_link/houdini/__init__.py
kitsupublisher/software_link/maya/__init__.py
kitsupublisher/software_link/maya/userSetup.py
kitsupublisher/ui_data/__init__.py
kitsupublisher/ui_data/color.py
kitsupublisher/ui_data/table_headers.py
kitsupublisher/ui_data/ui_values.py
kitsupublisher/utils/__init__.py
kitsupublisher/utils/colors.py
kitsupublisher/utils/connection.py
kitsupublisher/utils/data.py
kitsupublisher/utils/date.py
kitsupublisher/utils/error_window.py
kitsupublisher/utils/file.py
kitsupublisher/utils/format.py
kitsupublisher/utils/pyversion.py
kitsupublisher/utils/widgets.py
kitsupublisher/views/CustomToolBar.py
kitsupublisher/views/MainWindow.py
kitsupublisher-0.1.7.dist-info/LICENSE
kitsupublisher-0.1.7.dist-info/METADATA
kitsupublisher-0.1.7.dist-info/WHEEL
kitsupublisher-0.1.7.dist-info/entry_points.txt
kitsupublisher-0.1.7.dist-info/top_level.txt
kitsupublisher-0.1.7.dist-info/RECORD
