Metadata-Version: 2.1
Name: kitsupublisher
Version: 0.1.7
Summary: Application to publish previews to Kitsu from desktop environments
Home-page: http://www.cg-wire.com
Author: CGWire
Author-email: dev@cg-wire.com
License: MIT
Platform: UNKNOWN
License-File: LICENSE
Requires-Dist: gazu (==0.8.22)
Requires-Dist: qtazu
Requires-Dist: qt.py
Requires-Dist: dccutils
Requires-Dist: pytz
Requires-Dist: shiboken2
